control/__init__.py
control/config.py
control/contexts.py
control/core.py
control/decorators.py
control/exceptions.py
control/managers.py
control/models.py
control/utils.py
smart_clean-0.0.3.dist-info/METADATA
smart_clean-0.0.3.dist-info/WHEEL
smart_clean-0.0.3.dist-info/top_level.txt
smart_clean-0.0.3.dist-info/RECORD
