Metadata-Version: 2.4
Name: smart_clean
Version: 0.0.3
Summary: A minimal controllable thread cleaner.
Author: TESTAUTHOR
Requires-Python: >=3.6
Dynamic: author
Dynamic: requires-python
Dynamic: summary
